hatch_plugin.py
metadata.json
Tyradex/API.py
Tyradex/__init__.py
Tyradex/__main__.py
Tyradex/metadata.json
Tyradex/tdx_file.py
Tyradex/TyradexErrors/__init__.py
Tyradex/abc/__init__.py
tyradex-1.0.2.dist-info/METADATA
tyradex-1.0.2.dist-info/WHEEL
tyradex-1.0.2.dist-info/licenses/LICENSE
tyradex-1.0.2.dist-info/RECORD
