Metadata-Version: 2.4
Name: Tyradex
Version: 1.0.2
Summary: Tyradex for Python is an easy-to-use API based on the web version of Tyradex by Yarkis and Ashzuu.
Project-URL: Homepage, https://github.com/LassaInora/Tyradex
Project-URL: Issues, https://github.com/LassaInora/Tyradex/issues
Author-email: LassaInora <contact@lassainora.fr>
License-Expression: MIT
License-File: LICENSE
Keywords: API,Pokémon,Tyradex
Classifier: Operating System :: OS Independent
Classifier: Programming Language :: Python
Classifier: Programming Language :: Python :: 3
Classifier: Programming Language :: Python :: 3 :: Only
Classifier: Programming Language :: Python :: 3.8
Classifier: Programming Language :: Python :: 3.9
Classifier: Programming Language :: Python :: 3.10
Classifier: Programming Language :: Python :: 3.11
Classifier: Programming Language :: Python :: 3.12
Classifier: Programming Language :: Python :: 3.13
Classifier: Topic :: Software Development :: Libraries
Requires-Python: >=3.8
Requires-Dist: pratik
Requires-Dist: requests
